[
    {
        "exitcode": 23552,
        "id": "136.741",
        "name": "RunMuonEG2016C+RunMuonEG2016C+HLTDR2_2016+RECODR2_2016reHLT_skimMuonEG_HIPM+HARVESTDR2",
        "steps": [
            {
                "errors": 0,
                "status": "PASSED",
                "warnings": 0
            },
            {
                "errors": 0,
                "status": "FAILED",
                "warnings": 12
            },
            {
                "errors": -1,
                "status": "NOTRUN",
                "warnings": -1
            },
            {
                "errors": -1,
                "status": "NOTRUN",
                "warnings": -1
            }
        ]
    },
    {
        "exitcode": 34304,
        "id": "136.768",
        "name": "RunMuOnia2016E+RunMuOnia2016E+HLTDR2_2016+RECODR2_2016reHLT_skimMuOnia_HIPM+HARVESTDR2",
        "steps": [
            {
                "errors": 0,
                "status": "PASSED",
                "warnings": 0
            },
            {
                "errors": 0,
                "status": "PASSED",
                "warnings": 30
            },
            {
                "errors": 0,
                "status": "PASSED",
                "warnings": 88
            },
            {
                "errors": 0,
                "status": "FAILED",
                "warnings": 7
            }
        ]
    },
    {
        "exitcode": 0,
        "id": "4.29",
        "name": "RunMinBias2011B+RunMinBias2011B+HLTD+RECODR1reHLT+HARVESTDR1reHLT+SKIMDreHLT",
        "steps": [
            {
                "errors": 0,
                "status": "PASSED",
                "warnings": 0
            },
            {
                "errors": 0,
                "status": "PASSED",
                "warnings": 246
            },
            {
                "errors": 16,
                "status": "PASSED",
                "warnings": 10270
            },
            {
                "errors": 1,
                "status": "PASSED",
                "warnings": 9
            },
            {
                "errors": 16,
                "status": "PASSED",
                "warnings": 444
            }
        ]
    },
    {
        "exitcode": 0,
        "id": "4.55",
        "name": "RunJet2012B+RunJet2012B+HLTD+RECODR1reHLT+HARVESTDR1reHLT",
        "steps": [
            {
                "errors": 0,
                "status": "PASSED",
                "warnings": 0
            },
            {
                "errors": 0,
                "status": "PASSED",
                "warnings": 93
            },
            {
                "errors": 0,
                "status": "PASSED",
                "warnings": 13826
            },
            {
                "errors": 1,
                "status": "PASSED",
                "warnings": 9
            }
        ]
    },
    {
        "exitcode": 0,
        "id": "4.57",
        "name": "ZElSkim2012B+ZElSkim2012B+HLTDSKIM+RECODR1reHLT+HARVESTDR1reHLT",
        "steps": [
            {
                "errors": 0,
                "status": "PASSED",
                "warnings": 0
            },
            {
                "errors": 0,
                "status": "PASSED",
                "warnings": 137
            },
            {
                "errors": 0,
                "status": "PASSED",
                "warnings": 19245
            },
            {
                "errors": 1,
                "status": "PASSED",
                "warnings": 10
            }
        ]
    },
    {
        "exitcode": 0,
        "id": "4.67",
        "name": "ZElSkim2012C+ZElSkim2012C+HLTDSKIM+RECODR1reHLT+HARVESTDR1reHLT",
        "steps": [
            {
                "errors": 0,
                "status": "PASSED",
                "warnings": 0
            },
            {
                "errors": 0,
                "status": "PASSED",
                "warnings": 153
            },
            {
                "errors": 8,
                "status": "PASSED",
                "warnings": 19899
            },
            {
                "errors": 1,
                "status": "PASSED",
                "warnings": 10
            }
        ]
    },
    {
        "exitcode": 0,
        "id": "4.74",
        "name": "RunEl2012D+RunEl2012D+HLTD+RECODR1reHLT+HARVESTDR1reHLT",
        "steps": [
            {
                "errors": 0,
                "status": "PASSED",
                "warnings": 0
            },
            {
                "errors": 0,
                "status": "PASSED",
                "warnings": 115
            },
            {
                "errors": 8,
                "status": "PASSED",
                "warnings": 14477
            },
            {
                "errors": 1,
                "status": "PASSED",
                "warnings": 9
            }
        ]
    },
    {
        "exitcode": 0,
        "id": "4.76",
        "name": "ZMuSkim2012D+ZMuSkim2012D+HLTDSKIM2+RECODR1reHLT2+HARVESTDR1reHLT",
        "steps": [
            {
                "errors": 0,
                "status": "PASSED",
                "warnings": 0
            },
            {
                "errors": 0,
                "status": "PASSED",
                "warnings": 80
            },
            {
                "errors": 8,
                "status": "PASSED",
                "warnings": 17659
            },
            {
                "errors": 1,
                "status": "PASSED",
                "warnings": 10
            }
        ]
    },
    {
        "exitcode": 0,
        "id": "4.77",
        "name": "ZElSkim2012D+ZElSkim2012D+HLTDSKIM+RECODR1reHLT+HARVESTDR1reHLT",
        "steps": [
            {
                "errors": 0,
                "status": "PASSED",
                "warnings": 0
            },
            {
                "errors": 0,
                "status": "PASSED",
                "warnings": 146
            },
            {
                "errors": 9,
                "status": "PASSED",
                "warnings": 18005
            },
            {
                "errors": 1,
                "status": "PASSED",
                "warnings": 10
            }
        ]
    },
    {
        "exitcode": 0,
        "id": "134.702",
        "name": "RunDoubleEG2015B+RunDoubleEG2015B+HLTDR2_50ns+RECODR2_50nsreHLT_HIPM+HARVESTDR2",
        "steps": [
            {
                "errors": 0,
                "status": "PASSED",
                "warnings": 0
            },
            {
                "errors": 0,
                "status": "PASSED",
                "warnings": 194
            },
            {
                "errors": 208,
                "status": "PASSED",
                "warnings": 11784
            },
            {
                "errors": 1,
                "status": "PASSED",
                "warnings": 9
            }
        ]
    },
    {
        "exitcode": 0,
        "id": "134.705",
        "name": "RunMET2015B+RunMET2015B+HLTDR2_50ns+RECODR2_50nsreHLT_HIPM+HARVESTDR2",
        "steps": [
            {
                "errors": 0,
                "status": "PASSED",
                "warnings": 0
            },
            {
                "errors": 0,
                "status": "PASSED",
                "warnings": 168
            },
            {
                "errors": 208,
                "status": "PASSED",
                "warnings": 15114
            },
            {
                "errors": 1,
                "status": "PASSED",
                "warnings": 12
            }
        ]
    },
    {
        "exitcode": 0,
        "id": "134.902",
        "name": "RunDoubleEG2015D+RunDoubleEG2015D+HLTDR2_25ns+RECODR2_25nsreHLT_HIPM+HARVESTDR2",
        "steps": [
            {
                "errors": 0,
                "status": "PASSED",
                "warnings": 0
            },
            {
                "errors": 0,
                "status": "PASSED",
                "warnings": 297
            },
            {
                "errors": 201,
                "status": "PASSED",
                "warnings": 15454
            },
            {
                "errors": 1,
                "status": "PASSED",
                "warnings": 9
            }
        ]
    },
    {
        "exitcode": 0,
        "id": "134.912",
        "name": "RunZeroBias2015D+RunZeroBias2015D+HLTDR2_25ns+RECODR2_25nsreHLT_HIPM+HARVESTDR2",
        "steps": [
            {
                "errors": 0,
                "status": "PASSED",
                "warnings": 0
            },
            {
                "errors": 0,
                "status": "PASSED",
                "warnings": 186
            },
            {
                "errors": 201,
                "status": "PASSED",
                "warnings": 4553
            },
            {
                "errors": 1,
                "status": "PASSED",
                "warnings": 9
            }
        ]
    },
    {
        "exitcode": 0,
        "id": "134.99601",
        "name": "RunJetHT2015HLHS+RunJetHT2015HLHS+HLTDR2_25ns+RECODR2_25nsreHLT_HIPM+HARVESTDR2",
        "steps": [
            {
                "errors": 0,
                "status": "PASSED",
                "warnings": 0
            },
            {
                "errors": 0,
                "status": "PASSED",
                "warnings": 199
            },
            {
                "errors": 200,
                "status": "PASSED",
                "warnings": 13063
            },
            {
                "errors": 1,
                "status": "PASSED",
                "warnings": 9
            }
        ]
    },
    {
        "exitcode": 0,
        "id": "135.1",
        "name": "TTbar_13+TTbarFS_13+HARVESTUP15FS+MINIAODMCUP15FS",
        "steps": [
            {
                "errors": 0,
                "status": "PASSED",
                "warnings": 2568
            },
            {
                "errors": 4,
                "status": "PASSED",
                "warnings": 3
            },
            {
                "errors": 0,
                "status": "PASSED",
                "warnings": 282
            }
        ]
    },
    {
        "exitcode": 0,
        "id": "135.12",
        "name": "QCD_Pt_80_120_13+QCD_Pt_80_120FS_13+HARVESTUP15FS+MINIAODMCUP15FS",
        "steps": [
            {
                "errors": 0,
                "status": "PASSED",
                "warnings": 1069
            },
            {
                "errors": 4,
                "status": "PASSED",
                "warnings": 3
            },
            {
                "errors": 0,
                "status": "PASSED",
                "warnings": 381
            }
        ]
    },
    {
        "exitcode": 0,
        "id": "135.2",
        "name": "SingleMuPt10_UP15+SingleMuPt10FS_UP15+HARVESTUP15FS+MINIAODMCUP15FS",
        "steps": [
            {
                "errors": 0,
                "status": "PASSED",
                "warnings": 120
            },
            {
                "errors": 4,
                "status": "PASSED",
                "warnings": 3
            },
            {
                "errors": 0,
                "status": "PASSED",
                "warnings": 163
            }
        ]
    },
    {
        "exitcode": 0,
        "id": "135.4",
        "name": "ZEE_13+ZEEFS_13+HARVESTUP15FS+MINIAODMCUP15FS",
        "steps": [
            {
                "errors": 0,
                "status": "PASSED",
                "warnings": 893
            },
            {
                "errors": 4,
                "status": "PASSED",
                "warnings": 3
            },
            {
                "errors": 0,
                "status": "PASSED",
                "warnings": 145
            }
        ]
    },
    {
        "exitcode": 0,
        "id": "135.5",
        "name": "ZTT_13+ZTTFS_13+HARVESTUP15FS+MINIAODMCUP15FS",
        "steps": [
            {
                "errors": 0,
                "status": "PASSED",
                "warnings": 573
            },
            {
                "errors": 4,
                "status": "PASSED",
                "warnings": 3
            },
            {
                "errors": 0,
                "status": "PASSED",
                "warnings": 256
            }
        ]
    },
    {
        "exitcode": 0,
        "id": "135.7",
        "name": "H125GGgluonfusion_13+H125GGgluonfusionFS_13+HARVESTUP15FS+MINIAODMCUP15FS",
        "steps": [
            {
                "errors": 0,
                "status": "PASSED",
                "warnings": 1513
            },
            {
                "errors": 4,
                "status": "PASSED",
                "warnings": 3
            },
            {
                "errors": 0,
                "status": "PASSED",
                "warnings": 199
            }
        ]
    },
    {
        "exitcode": 0,
        "id": "136.723",
        "name": "RunDoubleMuon2016B+RunDoubleMuon2016B+HLTDR2_2016+RECODR2_2016reHLT_HIPM+HARVESTDR2",
        "steps": [
            {
                "errors": 0,
                "status": "PASSED",
                "warnings": 0
            },
            {
                "errors": 1,
                "status": "PASSED",
                "warnings": 8331
            },
            {
                "errors": 9,
                "status": "PASSED",
                "warnings": 14105
            },
            {
                "errors": 0,
                "status": "PASSED",
                "warnings": 9
            }
        ]
    },
    {
        "exitcode": 0,
        "id": "136.725",
        "name": "RunMET2016B+RunMET2016B+HLTDR2_2016+RECODR2_2016reHLT_HIPM+HARVESTDR2",
        "steps": [
            {
                "errors": 0,
                "status": "PASSED",
                "warnings": 0
            },
            {
                "errors": 1,
                "status": "PASSED",
                "warnings": 10462
            },
            {
                "errors": 9,
                "status": "PASSED",
                "warnings": 17356
            },
            {
                "errors": 0,
                "status": "PASSED",
                "warnings": 9
            }
        ]
    },
    {
        "exitcode": 0,
        "id": "136.727",
        "name": "RunDoubleEGPrpt2016B+RunDoubleEGPrpt2016B+HLTDR2_2016+RECODR2_2016reHLT_HIPM+HARVESTDR2",
        "steps": [
            {
                "errors": 0,
                "status": "PASSED",
                "warnings": 0
            },
            {
                "errors": 7,
                "status": "PASSED",
                "warnings": 12674
            },
            {
                "errors": 9,
                "status": "PASSED",
                "warnings": 12922
            },
            {
                "errors": 0,
                "status": "PASSED",
                "warnings": 10
            }
        ]
    },
    {
        "exitcode": 0,
        "id": "136.731",
        "name": "RunSinglePh2016B+RunSinglePh2016B+HLTDR2_2016+RECODR2_2016reHLT_skimSinglePh_HIPM+HARVESTDR2",
        "steps": [
            {
                "errors": 0,
                "status": "PASSED",
                "warnings": 0
            },
            {
                "errors": 1,
                "status": "PASSED",
                "warnings": 20425
            },
            {
                "errors": 9,
                "status": "PASSED",
                "warnings": 18404
            },
            {
                "errors": 0,
                "status": "PASSED",
                "warnings": 9
            }
        ]
    },
    {
        "exitcode": 0,
        "id": "136.732",
        "name": "RunZeroBias2016B+RunZeroBias2016B+HLTDR2_2016+RECODR2_2016reHLT_HIPM+HARVESTDR2",
        "steps": [
            {
                "errors": 0,
                "status": "PASSED",
                "warnings": 0
            },
            {
                "errors": 1,
                "status": "PASSED",
                "warnings": 5497
            },
            {
                "errors": 43,
                "status": "PASSED",
                "warnings": 10890
            },
            {
                "errors": 0,
                "status": "PASSED",
                "warnings": 9
            }
        ]
    },
    {
        "exitcode": 0,
        "id": "136.7321",
        "name": "RunZeroBias2016BnewL1repack+RunZeroBias2016BnewL1repack+HLTDR2newL1repack_2016+RECODR2newL1repack_2016reHLT_HIPM+HARVESTDR2",
        "steps": [
            {
                "errors": 0,
                "status": "PASSED",
                "warnings": 0
            },
            {
                "errors": 1,
                "status": "PASSED",
                "warnings": 7597
            },
            {
                "errors": 43,
                "status": "PASSED",
                "warnings": 10503
            },
            {
                "errors": 0,
                "status": "PASSED",
                "warnings": 9
            }
        ]
    },
    {
        "exitcode": 0,
        "id": "136.734",
        "name": "RunMuOnia2016B+RunMuOnia2016B+HLTDR2_2016+RECODR2_2016reHLT_skimMuOnia_HIPM+HARVESTDR2",
        "steps": [
            {
                "errors": 0,
                "status": "PASSED",
                "warnings": 0
            },
            {
                "errors": 1,
                "status": "PASSED",
                "warnings": 12130
            },
            {
                "errors": 9,
                "status": "PASSED",
                "warnings": 12506
            },
            {
                "errors": 0,
                "status": "PASSED",
                "warnings": 9
            }
        ]
    },
    {
        "exitcode": 0,
        "id": "136.752",
        "name": "RunMuonEG2016D+RunMuonEG2016D+HLTDR2_2016+RECODR2_2016reHLT_skimMuonEG_HIPM+HARVESTDR2",
        "steps": [
            {
                "errors": 0,
                "status": "PASSED",
                "warnings": 0
            },
            {
                "errors": 7,
                "status": "PASSED",
                "warnings": 17260
            },
            {
                "errors": 5630,
                "status": "PASSED",
                "warnings": 20641
            },
            {
                "errors": 0,
                "status": "PASSED",
                "warnings": 9
            }
        ]
    },
    {
        "exitcode": 0,
        "id": "136.754",
        "name": "RunSingleMu2016D+RunSingleMu2016D+HLTDR2_2016+RECODR2_2016reHLT_HIPM+HARVESTDR2",
        "steps": [
            {
                "errors": 0,
                "status": "PASSED",
                "warnings": 0
            },
            {
                "errors": 1,
                "status": "PASSED",
                "warnings": 13748
            },
            {
                "errors": 5313,
                "status": "PASSED",
                "warnings": 14640
            },
            {
                "errors": 0,
                "status": "PASSED",
                "warnings": 10
            }
        ]
    },
    {
        "exitcode": 0,
        "id": "136.755",
        "name": "RunSinglePh2016D+RunSinglePh2016D+HLTDR2_2016+RECODR2_2016reHLT_skimSinglePh_HIPM+HARVESTDR2",
        "steps": [
            {
                "errors": 0,
                "status": "PASSED",
                "warnings": 0
            },
            {
                "errors": 4,
                "status": "PASSED",
                "warnings": 12948
            },
            {
                "errors": 5597,
                "status": "PASSED",
                "warnings": 15158
            },
            {
                "errors": 0,
                "status": "PASSED",
                "warnings": 9
            }
        ]
    },
    {
        "exitcode": 0,
        "id": "136.767",
        "name": "RunZeroBias2016E+RunZeroBias2016E+HLTDR2_2016+RECODR2_2016reHLT_HIPM+HARVESTDR2",
        "steps": [
            {
                "errors": 0,
                "status": "PASSED",
                "warnings": 0
            },
            {
                "errors": 1,
                "status": "PASSED",
                "warnings": 9744
            },
            {
                "errors": 6959,
                "status": "PASSED",
                "warnings": 14701
            },
            {
                "errors": 0,
                "status": "PASSED",
                "warnings": 9
            }
        ]
    },
    {
        "exitcode": 0,
        "id": "145.0",
        "name": "HydjetQ_MinBias_5020GeV+HydjetQ_MinBias_5020GeVINPUT+DIGIHI+RECOHI+HARVESTHI",
        "steps": [
            {
                "errors": 0,
                "status": "PASSED",
                "warnings": 0
            },
            {
                "errors": 6,
                "status": "PASSED",
                "warnings": 152
            },
            {
                "errors": 20,
                "status": "PASSED",
                "warnings": 183
            },
            {
                "errors": 6,
                "status": "PASSED",
                "warnings": 10
            }
        ]
    },
    {
        "exitcode": 0,
        "id": "281.0",
        "name": "EPOS_PPb_8160GeV_MinimumBias+EPOS_PPb_8160GeV_MinimumBias+DIGIUP15_PPb+RECOUP15_PPb+HARVESTUP15_PPb",
        "steps": [
            {
                "errors": 1,
                "status": "PASSED",
                "warnings": 53
            },
            {
                "errors": 0,
                "status": "PASSED",
                "warnings": 56
            },
            {
                "errors": 20,
                "status": "PASSED",
                "warnings": 1299
            },
            {
                "errors": 3,
                "status": "PASSED",
                "warnings": 11
            }
        ]
    },
    {
        "exitcode": 0,
        "id": "518.0",
        "name": "DYTollJets_LO_Mad_13TeV_py8_taurhonu+DYToll01234Jets_5f_LO_MLM_Madgraph_LHE_13TeV+Hadronizer_TuneCUETP8M1_13TeV_MLM_5f_max4j_LHE_pythia8_taurhonu+HARVESTGEN2",
        "steps": [
            {
                "errors": 0,
                "status": "PASSED",
                "warnings": 11
            },
            {
                "errors": 0,
                "status": "PASSED",
                "warnings": 138
            },
            {
                "errors": 0,
                "status": "PASSED",
                "warnings": 0
            }
        ]
    },
    {
        "exitcode": 0,
        "id": "529.0",
        "name": "DYTollJets_LO_Mad_13TeV_py8_Ta_taurhonu+DYToll01234Jets_5f_LO_MLM_Madgraph_LHE_13TeV+Hadronizer_TuneCUETP8M1_13TeV_MLM_5f_max4j_LHE_pythia8_Tauola_taurhonu+HARVESTGEN2",
        "steps": [
            {
                "errors": 0,
                "status": "PASSED",
                "warnings": 14
            },
            {
                "errors": 0,
                "status": "PASSED",
                "warnings": 121
            },
            {
                "errors": 0,
                "status": "PASSED",
                "warnings": 0
            }
        ]
    },
    {
        "exitcode": 0,
        "id": "1306.0",
        "name": "SingleMuPt1_UP15+SingleMuPt1_UP15INPUT+DIGIUP15+RECOUP15+HARVESTUP15",
        "steps": [
            {
                "errors": 0,
                "status": "PASSED",
                "warnings": 0
            },
            {
                "errors": 0,
                "status": "PASSED",
                "warnings": 386
            },
            {
                "errors": 0,
                "status": "PASSED",
                "warnings": 270
            },
            {
                "errors": 0,
                "status": "PASSED",
                "warnings": 9
            }
        ]
    },
    {
        "exitcode": 0,
        "id": "1311.0",
        "name": "MinBias_13+MinBias_13INPUT+DIGIUP15+RECOMINUP15+HARVESTMINUP15+ALCAMINUP15",
        "steps": [
            {
                "errors": 0,
                "status": "PASSED",
                "warnings": 0
            },
            {
                "errors": 0,
                "status": "PASSED",
                "warnings": 366
            },
            {
                "errors": 0,
                "status": "PASSED",
                "warnings": 870
            },
            {
                "errors": 0,
                "status": "PASSED",
                "warnings": 9
            },
            {
                "errors": 0,
                "status": "PASSED",
                "warnings": 38
            }
        ]
    },
    {
        "exitcode": 0,
        "id": "1314.0",
        "name": "WpM_13+WpM_13INPUT+DIGIUP15+RECOUP15+HARVESTUP15",
        "steps": [
            {
                "errors": 0,
                "status": "PASSED",
                "warnings": 0
            },
            {
                "errors": 0,
                "status": "PASSED",
                "warnings": 1103
            },
            {
                "errors": 0,
                "status": "PASSED",
                "warnings": 581
            },
            {
                "errors": 0,
                "status": "PASSED",
                "warnings": 9
            }
        ]
    },
    {
        "exitcode": 0,
        "id": "1315.0",
        "name": "SingleElectronPt10_UP15+SingleElectronPt10_UP15INPUT+DIGIUP15+RECOUP15+HARVESTUP15",
        "steps": [
            {
                "errors": 0,
                "status": "PASSED",
                "warnings": 0
            },
            {
                "errors": 0,
                "status": "PASSED",
                "warnings": 347
            },
            {
                "errors": 0,
                "status": "PASSED",
                "warnings": 425
            },
            {
                "errors": 0,
                "status": "PASSED",
                "warnings": 9
            }
        ]
    },
    {
        "exitcode": 0,
        "id": "1318.0",
        "name": "SingleGammaPt10_UP15+SingleGammaPt10_UP15INPUT+DIGIUP15+RECOUP15+HARVESTUP15",
        "steps": [
            {
                "errors": 0,
                "status": "PASSED",
                "warnings": 0
            },
            {
                "errors": 0,
                "status": "PASSED",
                "warnings": 536
            },
            {
                "errors": 0,
                "status": "PASSED",
                "warnings": 452
            },
            {
                "errors": 0,
                "status": "PASSED",
                "warnings": 9
            }
        ]
    },
    {
        "exitcode": 0,
        "id": "1321.0",
        "name": "SingleMuPt100_UP15+SingleMuPt100_UP15INPUT+DIGIUP15+RECOUP15+HARVESTUP15",
        "steps": [
            {
                "errors": 0,
                "status": "PASSED",
                "warnings": 0
            },
            {
                "errors": 0,
                "status": "PASSED",
                "warnings": 412
            },
            {
                "errors": 0,
                "status": "PASSED",
                "warnings": 208
            },
            {
                "errors": 0,
                "status": "PASSED",
                "warnings": 9
            }
        ]
    },
    {
        "exitcode": 0,
        "id": "1323.0",
        "name": "NuGun_UP15+NuGun_UP15INPUT+DIGIUP15+RECOUP15+HARVESTUP15",
        "steps": [
            {
                "errors": 0,
                "status": "PASSED",
                "warnings": 0
            },
            {
                "errors": 0,
                "status": "PASSED",
                "warnings": 493
            },
            {
                "errors": 0,
                "status": "PASSED",
                "warnings": 236
            },
            {
                "errors": 0,
                "status": "PASSED",
                "warnings": 9
            }
        ]
    },
    {
        "exitcode": 0,
        "id": "1325.0",
        "name": "TTbar_13+TTbar_13INPUT+DIGIUP15+RECOUP15+HARVESTUP15+ALCATTUP15",
        "steps": [
            {
                "errors": 0,
                "status": "PASSED",
                "warnings": 0
            },
            {
                "errors": 0,
                "status": "PASSED",
                "warnings": 1926
            },
            {
                "errors": 0,
                "status": "PASSED",
                "warnings": 988
            },
            {
                "errors": 0,
                "status": "PASSED",
                "warnings": 9
            },
            {
                "errors": 0,
                "status": "PASSED",
                "warnings": 48
            }
        ]
    },
    {
        "exitcode": 0,
        "id": "1325.2",
        "name": "TTbar_13+TTbar_13INPUT+DIGIUP15+RECOUP15_trackingLowPU+HARVESTUP15",
        "steps": [
            {
                "errors": 0,
                "status": "PASSED",
                "warnings": 0
            },
            {
                "errors": 0,
                "status": "PASSED",
                "warnings": 1640
            },
            {
                "errors": 0,
                "status": "PASSED",
                "warnings": 887
            },
            {
                "errors": 0,
                "status": "PASSED",
                "warnings": 9
            }
        ]
    },
    {
        "exitcode": 0,
        "id": "1331.0",
        "name": "ZTT_13+ZTT_13INPUT+DIGIUP15+RECOUP15+HARVESTUP15",
        "steps": [
            {
                "errors": 0,
                "status": "PASSED",
                "warnings": 0
            },
            {
                "errors": 0,
                "status": "PASSED",
                "warnings": 193
            },
            {
                "errors": 0,
                "status": "PASSED",
                "warnings": 359
            },
            {
                "errors": 0,
                "status": "PASSED",
                "warnings": 9
            }
        ]
    },
    {
        "exitcode": 0,
        "id": "1332.0",
        "name": "H125GGgluonfusion_13+H125GGgluonfusion_13INPUT+DIGIUP15+RECOUP15+HARVESTUP15",
        "steps": [
            {
                "errors": 0,
                "status": "PASSED",
                "warnings": 0
            },
            {
                "errors": 0,
                "status": "PASSED",
                "warnings": 761
            },
            {
                "errors": 0,
                "status": "PASSED",
                "warnings": 1089
            },
            {
                "errors": 0,
                "status": "PASSED",
                "warnings": 9
            }
        ]
    },
    {
        "exitcode": 0,
        "id": "1334.0",
        "name": "QQH1352T_13+QQH1352T_13INPUT+DIGIUP15+RECOUP15+HARVESTUP15",
        "steps": [
            {
                "errors": 0,
                "status": "PASSED",
                "warnings": 0
            },
            {
                "errors": 0,
                "status": "PASSED",
                "warnings": 1033
            },
            {
                "errors": 0,
                "status": "PASSED",
                "warnings": 756
            },
            {
                "errors": 0,
                "status": "PASSED",
                "warnings": 9
            }
        ]
    },
    {
        "exitcode": 0,
        "id": "1340.0",
        "name": "PhiToMuMu_13+PhiToMuMu_13INPUT+DIGIUP15+RECOUP15+HARVESTUP15",
        "steps": [
            {
                "errors": 0,
                "status": "PASSED",
                "warnings": 0
            },
            {
                "errors": 0,
                "status": "PASSED",
                "warnings": 652
            },
            {
                "errors": 0,
                "status": "PASSED",
                "warnings": 826
            },
            {
                "errors": 0,
                "status": "PASSED",
                "warnings": 9
            }
        ]
    },
    {
        "exitcode": 0,
        "id": "1344.0",
        "name": "ZpEE_2250_13+ZpEE_2250_13INPUT+DIGIUP15+RECOUP15+HARVESTUP15",
        "steps": [
            {
                "errors": 0,
                "status": "PASSED",
                "warnings": 0
            },
            {
                "errors": 0,
                "status": "PASSED",
                "warnings": 3717
            },
            {
                "errors": 0,
                "status": "PASSED",
                "warnings": 1322
            },
            {
                "errors": 0,
                "status": "PASSED",
                "warnings": 9
            }
        ]
    },
    {
        "exitcode": 0,
        "id": "1345.0",
        "name": "ZpTT_1500_13+ZpTT_1500_13INPUT+DIGIUP15+RECOUP15+HARVESTUP15",
        "steps": [
            {
                "errors": 0,
                "status": "PASSED",
                "warnings": 0
            },
            {
                "errors": 0,
                "status": "PASSED",
                "warnings": 2047
            },
            {
                "errors": 0,
                "status": "PASSED",
                "warnings": 1101
            },
            {
                "errors": 0,
                "status": "PASSED",
                "warnings": 9
            }
        ]
    },
    {
        "exitcode": 0,
        "id": "1347.0",
        "name": "Upsilon1SToMuMu_13+Upsilon1SToMuMu_13INPUT+DIGIUP15+RECOUP15+HARVESTUP15",
        "steps": [
            {
                "errors": 0,
                "status": "PASSED",
                "warnings": 0
            },
            {
                "errors": 0,
                "status": "PASSED",
                "warnings": 1521
            },
            {
                "errors": 0,
                "status": "PASSED",
                "warnings": 791
            },
            {
                "errors": 0,
                "status": "PASSED",
                "warnings": 9
            }
        ]
    },
    {
        "exitcode": 0,
        "id": "1353.0",
        "name": "RSGravitonToGaGa_13+RSGravitonToGaGa_13INPUT+DIGIUP15+RECOUP15+HARVESTUP15",
        "steps": [
            {
                "errors": 0,
                "status": "PASSED",
                "warnings": 0
            },
            {
                "errors": 0,
                "status": "PASSED",
                "warnings": 2008
            },
            {
                "errors": 0,
                "status": "PASSED",
                "warnings": 1020
            },
            {
                "errors": 0,
                "status": "PASSED",
                "warnings": 9
            }
        ]
    },
    {
        "exitcode": 0,
        "id": "1360.0",
        "name": "TTbar012Jets_NLO_Mad_py8_Evt_13+TTbar012Jets_NLO_Mad_py8_Evt_13+DIGIUP15+RECOUP15+HARVESTUP15",
        "steps": [
            {
                "errors": 0,
                "status": "PASSED",
                "warnings": 103
            },
            {
                "errors": 0,
                "status": "PASSED",
                "warnings": 246
            },
            {
                "errors": 0,
                "status": "PASSED",
                "warnings": 482
            },
            {
                "errors": 0,
                "status": "PASSED",
                "warnings": 9
            }
        ]
    },
    {
        "exitcode": 0,
        "id": "1361.0",
        "name": "GluGluHToZZTo4L_M125_Pow_py8_Evt_13+GluGluHToZZTo4L_M125_Pow_py8_Evt_13+DIGIUP15+RECOUP15+HARVESTUP15",
        "steps": [
            {
                "errors": 0,
                "status": "PASSED",
                "warnings": 72
            },
            {
                "errors": 0,
                "status": "PASSED",
                "warnings": 1743
            },
            {
                "errors": 0,
                "status": "PASSED",
                "warnings": 1258
            },
            {
                "errors": 0,
                "status": "PASSED",
                "warnings": 9
            }
        ]
    },
    {
        "exitcode": 0,
        "id": "1365.0",
        "name": "BuToJpsiK_13+BuToJpsiK_13INPUT+DIGIUP15+RECOUP15+HARVESTUP15",
        "steps": [
            {
                "errors": 0,
                "status": "PASSED",
                "warnings": 0
            },
            {
                "errors": 0,
                "status": "PASSED",
                "warnings": 1063
            },
            {
                "errors": 0,
                "status": "PASSED",
                "warnings": 774
            },
            {
                "errors": 0,
                "status": "PASSED",
                "warnings": 9
            }
        ]
    },
    {
        "exitcode": 0,
        "id": "10424.0",
        "name": "TTbar_13+TTbar_13TeV_TuneCUETP8M1_2017NewFPix_GenSimFull+DigiFull_2017NewFPix+RecoFull_2017NewFPix+ALCAFull_2017NewFPix+HARVESTFull_2017NewFPix",
        "steps": [
            {
                "errors": 0,
                "status": "PASSED",
                "warnings": 46
            },
            {
                "errors": 0,
                "status": "PASSED",
                "warnings": 186
            },
            {
                "errors": 20,
                "status": "PASSED",
                "warnings": 1492
            },
            {
                "errors": 0,
                "status": "PASSED",
                "warnings": 65
            },
            {
                "errors": 0,
                "status": "PASSED",
                "warnings": 9
            }
        ]
    },
    {
        "exitcode": 0,
        "id": "20024.0",
        "name": "TTbar_13+TTbar_13TeV_TuneCUETP8M1_2023D1_GenSimHLBeamSpotFull+DigiFull_2023D1+RecoFullGlobal_2023D1+HARVESTFullGlobal_2023D1",
        "steps": [
            {
                "errors": 0,
                "status": "PASSED",
                "warnings": 51
            },
            {
                "errors": 0,
                "status": "PASSED",
                "warnings": 129
            },
            {
                "errors": 0,
                "status": "PASSED",
                "warnings": 1168
            },
            {
                "errors": 0,
                "status": "PASSED",
                "warnings": 15
            }
        ]
    },
    {
        "exitcode": 0,
        "id": "20025.0",
        "name": "ZEE_13+ZEE_13TeV_TuneCUETP8M1_2023D1_GenSimHLBeamSpotFull+DigiFull_2023D1+RecoFullGlobal_2023D1+HARVESTFullGlobal_2023D1",
        "steps": [
            {
                "errors": 0,
                "status": "PASSED",
                "warnings": 32
            },
            {
                "errors": 0,
                "status": "PASSED",
                "warnings": 172
            },
            {
                "errors": 0,
                "status": "PASSED",
                "warnings": 807
            },
            {
                "errors": 0,
                "status": "PASSED",
                "warnings": 15
            }
        ]
    },
    {
        "exitcode": 0,
        "id": "20425.0",
        "name": "ZEE_13+ZEE_13TeV_TuneCUETP8M1_2023D2_GenSimHLBeamSpotFull+DigiFull_2023D2+RecoFullGlobal_2023D2+HARVESTFullGlobal_2023D2",
        "steps": [
            {
                "errors": 0,
                "status": "PASSED",
                "warnings": 55
            },
            {
                "errors": 0,
                "status": "PASSED",
                "warnings": 133
            },
            {
                "errors": 0,
                "status": "PASSED",
                "warnings": 846
            },
            {
                "errors": 0,
                "status": "PASSED",
                "warnings": 15
            }
        ]
    },
    {
        "exitcode": 0,
        "id": "20826.0",
        "name": "QCD_Pt_600_800_13+QCD_Pt_600_800_13TeV_TuneCUETP8M1_2023D3_GenSimHLBeamSpotFull+DigiFull_2023D3+RecoFullGlobal_2023D3+HARVESTFullGlobal_2023D3",
        "steps": [
            {
                "errors": 0,
                "status": "PASSED",
                "warnings": 42
            },
            {
                "errors": 0,
                "status": "PASSED",
                "warnings": 91
            },
            {
                "errors": 11,
                "status": "PASSED",
                "warnings": 1027
            },
            {
                "errors": 0,
                "status": "PASSED",
                "warnings": 15
            }
        ]
    },
    {
        "exitcode": 0,
        "id": "21224.0",
        "name": "TTbar_13+TTbar_13TeV_TuneCUETP8M1_2023D4_GenSimHLBeamSpotFull+DigiFull_2023D4+RecoFullLocal_2023D4",
        "steps": [
            {
                "errors": 0,
                "status": "PASSED",
                "warnings": 38
            },
            {
                "errors": 0,
                "status": "PASSED",
                "warnings": 37
            },
            {
                "errors": 0,
                "status": "PASSED",
                "warnings": 104
            }
        ]
    },
    {
        "exitcode": 0,
        "id": "25207.0",
        "name": "NuGun_UP15+NuGun_UP15INPUT+DIGIUP15_PU25+RECOUP15_PU25+HARVESTUP15_PU25",
        "steps": [
            {
                "errors": 0,
                "status": "PASSED",
                "warnings": 0
            },
            {
                "errors": 0,
                "status": "PASSED",
                "warnings": 1183
            },
            {
                "errors": 0,
                "status": "PASSED",
                "warnings": 1243
            },
            {
                "errors": 0,
                "status": "PASSED",
                "warnings": 9
            }
        ]
    },
    {
        "exitcode": 0,
        "id": "25210.0",
        "name": "TTbar012Jets_NLO_Mad_py8_Evt_13+TTbar012Jets_NLO_Mad_py8_Evt_13+DIGIUP15_PU25+RECOUP15_PU25+HARVESTUP15_PU25",
        "steps": [
            {
                "errors": 0,
                "status": "PASSED",
                "warnings": 116
            },
            {
                "errors": 0,
                "status": "PASSED",
                "warnings": 459
            },
            {
                "errors": 0,
                "status": "PASSED",
                "warnings": 93
            },
            {
                "errors": 0,
                "status": "PASSED",
                "warnings": 9
            }
        ]
    },
    {
        "exitcode": 0,
        "id": "25402.0",
        "name": "TTbar_13+FS_TTbar_13_UP15_PU25+HARVESTUP15FS+MINIAODMCUP15FS",
        "steps": [
            {
                "errors": 0,
                "status": "PASSED",
                "warnings": 880
            },
            {
                "errors": 4,
                "status": "PASSED",
                "warnings": 3
            },
            {
                "errors": 0,
                "status": "PASSED",
                "warnings": 587
            }
        ]
    },
    {
        "exitcode": 0,
        "id": "25406.0",
        "name": "ZMM_13+FS_ZMM_13_UP15_PU25+HARVESTUP15FS+MINIAODMCUP15FS",
        "steps": [
            {
                "errors": 24,
                "status": "PASSED",
                "warnings": 1140
            },
            {
                "errors": 4,
                "status": "PASSED",
                "warnings": 3
            },
            {
                "errors": 0,
                "status": "PASSED",
                "warnings": 101
            }
        ]
    },
    {
        "exitcode": 0,
        "id": "25407.0",
        "name": "NuGun_UP15+FS_NuGun_UP15_UP15_PU25+HARVESTUP15FS+MINIAODMCUP15FS",
        "steps": [
            {
                "errors": 0,
                "status": "PASSED",
                "warnings": 952
            },
            {
                "errors": 4,
                "status": "PASSED",
                "warnings": 3
            },
            {
                "errors": 0,
                "status": "PASSED",
                "warnings": 430
            }
        ]
    },
    {
        "exitcode": 0,
        "id": "50202.0",
        "name": "TTbar_13+TTbar_13INPUT+DIGIUP15_PU50+RECOUP15_PU50+HARVESTUP15_PU50",
        "steps": [
            {
                "errors": 0,
                "status": "PASSED",
                "warnings": 0
            },
            {
                "errors": 0,
                "status": "PASSED",
                "warnings": 115
            },
            {
                "errors": 0,
                "status": "PASSED",
                "warnings": 1932
            },
            {
                "errors": 3,
                "status": "PASSED",
                "warnings": 11
            }
        ]
    },
    {
        "exitcode": 0,
        "id": "50203.0",
        "name": "H125GGgluonfusion_13+H125GGgluonfusion_13INPUT+DIGIUP15_PU50+RECOUP15_PU50+HARVESTUP15_PU50",
        "steps": [
            {
                "errors": 0,
                "status": "PASSED",
                "warnings": 0
            },
            {
                "errors": 0,
                "status": "PASSED",
                "warnings": 45
            },
            {
                "errors": 0,
                "status": "PASSED",
                "warnings": 2491
            },
            {
                "errors": 3,
                "status": "PASSED",
                "warnings": 11
            }
        ]
    },
    {
        "exitcode": 0,
        "id": "50205.0",
        "name": "ZTT_13+ZTT_13INPUT+DIGIUP15_PU50+RECOUP15_PU50+HARVESTUP15_PU50",
        "steps": [
            {
                "errors": 0,
                "status": "PASSED",
                "warnings": 0
            },
            {
                "errors": 0,
                "status": "PASSED",
                "warnings": 56
            },
            {
                "errors": 0,
                "status": "PASSED",
                "warnings": 1465
            },
            {
                "errors": 3,
                "status": "PASSED",
                "warnings": 11
            }
        ]
    },
    {
        "exitcode": 0,
        "id": "50207.0",
        "name": "NuGun_UP15+NuGun_UP15INPUT+DIGIUP15_PU50+RECOUP15_PU50+HARVESTUP15_PU50",
        "steps": [
            {
                "errors": 0,
                "status": "PASSED",
                "warnings": 0
            },
            {
                "errors": 0,
                "status": "PASSED",
                "warnings": 155
            },
            {
                "errors": 0,
                "status": "PASSED",
                "warnings": 1902
            },
            {
                "errors": 3,
                "status": "PASSED",
                "warnings": 11
            }
        ]
    },
    {
        "exitcode": 0,
        "id": "50208.0",
        "name": "SMS-T1tttt_mGl-1500_mLSP-100_13+SMS-T1tttt_mGl-1500_mLSP-100_13INPUT+DIGIUP15_PU50+RECOUP15_PU50+HARVESTUP15_PU50",
        "steps": [
            {
                "errors": 0,
                "status": "PASSED",
                "warnings": 0
            },
            {
                "errors": 0,
                "status": "PASSED",
                "warnings": 177
            },
            {
                "errors": 0,
                "status": "PASSED",
                "warnings": 1243
            },
            {
                "errors": 3,
                "status": "PASSED",
                "warnings": 11
            }
        ]
    },
    {
        "exitcode": 0,
        "id": "139901.0",
        "name": "ZMM_13_HS+ZMM_13_HSINPUT+DIGIUP15+RECOUP15+HARVESTUP15",
        "steps": [
            {
                "errors": 0,
                "status": "PASSED",
                "warnings": 0
            },
            {
                "errors": 0,
                "status": "PASSED",
                "warnings": 1065
            },
            {
                "errors": 0,
                "status": "PASSED",
                "warnings": 789
            },
            {
                "errors": 0,
                "status": "PASSED",
                "warnings": 9
            }
        ]
    },
    {
        "exitcode": 0,
        "id": "139902.0",
        "name": "TTbar_13_HS+TTbar_13_HSINPUT+DIGIUP15+RECOUP15+HARVESTUP15",
        "steps": [
            {
                "errors": 0,
                "status": "PASSED",
                "warnings": 0
            },
            {
                "errors": 0,
                "status": "PASSED",
                "warnings": 1068
            },
            {
                "errors": 0,
                "status": "PASSED",
                "warnings": 1028
            },
            {
                "errors": 0,
                "status": "PASSED",
                "warnings": 9
            }
        ]
    },
    {
        "exitcode": 0,
        "id": "250403.0",
        "name": "H125GGgluonfusion_13+FS_H125GGgluonfusion_13_PRMXUP15_PU25+HARVESTUP15FS+MINIAODMCUP15FS",
        "steps": [
            {
                "errors": 0,
                "status": "PASSED",
                "warnings": 1169
            },
            {
                "errors": 4,
                "status": "PASSED",
                "warnings": 3
            },
            {
                "errors": 0,
                "status": "PASSED",
                "warnings": 511
            }
        ]
    },
    {
        "exitcode": 0,
        "id": "250408.0",
        "name": "QCD_FlatPt_15_3000HS_13+FS_QCD_FlatPt_15_3000HS_13_PRMXUP15_PU25+HARVESTUP15FS+MINIAODMCUP15FS",
        "steps": [
            {
                "errors": 0,
                "status": "PASSED",
                "warnings": 1793
            },
            {
                "errors": 4,
                "status": "PASSED",
                "warnings": 3
            },
            {
                "errors": 0,
                "status": "PASSED",
                "warnings": 494
            }
        ]
    },
    {
        "exitcode": 0,
        "id": "250409.0",
        "name": "SMS-T1tttt_mGl-1500_mLSP-100_13+FS_SMS-T1tttt_mGl-1500_mLSP-100_13_PRMXUP15_PU25+HARVESTUP15FS+MINIAODMCUP15FS",
        "steps": [
            {
                "errors": 32,
                "status": "PASSED",
                "warnings": 2243
            },
            {
                "errors": 4,
                "status": "PASSED",
                "warnings": 3
            },
            {
                "errors": 0,
                "status": "PASSED",
                "warnings": 268
            }
        ]
    },
    {
        "exitcode": 0,
        "id": "500200.0",
        "name": "ZEE_13+ZEE_13INPUT+DIGIPRMXUP15_PU50+RECOPRMXUP15_PU50+HARVESTUP15_PU50",
        "steps": [
            {
                "errors": 0,
                "status": "PASSED",
                "warnings": 0
            },
            {
                "errors": 0,
                "status": "PASSED",
                "warnings": 432
            },
            {
                "errors": 0,
                "status": "PASSED",
                "warnings": 1764
            },
            {
                "errors": 3,
                "status": "PASSED",
                "warnings": 11
            }
        ]
    }
]
